MANIFEST.in
README.md
setup.cfg
setup.py
upc.py
upc.egg-info/PKG-INFO
upc.egg-info/SOURCES.txt
upc.egg-info/dependency_links.txt
upc.egg-info/entry_points.txt
upc.egg-info/requires.txt
upc.egg-info/top_level.txt