Metadata-Version: 1.1
Name: upc
Version: 0.0.2
Summary: A simple command-line tool for managing upyun files.
Home-page: http://github.com/likang/upc
Author: Kang Li
Author-email: i@likang.me
License: MIT
Download-URL: http://pypi.python.org/pypi/upc
Keywords: upyun,console,commandline,command
Platform: any
Classifier: Intended Audience :: Developers
Classifier: License :: OSI Approved :: MIT License
Classifier: Operating System :: OS Independent
Classifier: Programming Language :: Python
Classifier: Programming Language :: Python :: 2
Classifier: Programming Language :: Python :: 2.6
Classifier: Programming Language :: Python :: 2.7
Classifier: Programming Language :: Python :: 3
Classifier: Programming Language :: Python :: 3.3
